data_rentgen/VERSION
data_rentgen/__init__.py
data_rentgen/py.typed
data_rentgen/consumer/__init__.py
data_rentgen/consumer/__main__.py
data_rentgen/consumer/saver.py
data_rentgen/consumer/subscribers.py
data_rentgen/consumer/extractors/__init__.py
data_rentgen/consumer/extractors/batch_extraction_result.py
data_rentgen/consumer/extractors/batch_extractor.py
data_rentgen/consumer/extractors/generic/__init__.py
data_rentgen/consumer/extractors/generic/column_lineage.py
data_rentgen/consumer/extractors/generic/dataset.py
data_rentgen/consumer/extractors/generic/io.py
data_rentgen/consumer/extractors/generic/job.py
data_rentgen/consumer/extractors/generic/operation.py
data_rentgen/consumer/extractors/generic/run.py
data_rentgen/consumer/extractors/impl/__init__.py
data_rentgen/consumer/extractors/impl/airflow_dag.py
data_rentgen/consumer/extractors/impl/airflow_task.py
data_rentgen/consumer/extractors/impl/dbt.py
data_rentgen/consumer/extractors/impl/flink.py
data_rentgen/consumer/extractors/impl/hive.py
data_rentgen/consumer/extractors/impl/interface.py
data_rentgen/consumer/extractors/impl/spark.py
data_rentgen/consumer/extractors/impl/unknown.py
data_rentgen/consumer/settings/__init__.py
data_rentgen/consumer/settings/consumer.py
data_rentgen/consumer/settings/kafka.py
data_rentgen/consumer/settings/producer.py
data_rentgen/consumer/settings/security/__init__.py
data_rentgen/consumer/settings/security/anonymous.py
data_rentgen/consumer/settings/security/base.py
data_rentgen/consumer/settings/security/gssapi.py
data_rentgen/consumer/settings/security/plain.py
data_rentgen/consumer/settings/security/scram.py
data_rentgen/db/__init__.py
data_rentgen/db/factory.py
data_rentgen/db/settings.py
data_rentgen/db/migrations/__init__.py
data_rentgen/db/migrations/__main__.py
data_rentgen/db/migrations/alembic.ini
data_rentgen/db/migrations/env.py
data_rentgen/db/migrations/versions/2024-06-27_026de1556610_create_job.py
data_rentgen-0.4.8.dist-info/licenses/LICENSE.txt
data_rentgen-0.4.8.dist-info/METADATA
data_rentgen-0.4.8.dist-info/WHEEL
data_rentgen-0.4.8.dist-info/top_level.txt
data_rentgen-0.4.8.dist-info/RECORD
