Metadata-Version: 2.4
Name: data-rentgen
Version: 0.4.8
Summary: Data.Rentgen REST API + Kafka consumer
Author-email: MWS Data Bridge <onetools@mts.ru>
License: Apache-2.0
Project-URL: Homepage, https://github.com/MobileTeleSystems/data-rentgen
Project-URL: Documentation, https://data-rentgen.readthedocs.io/
Project-URL: Source, https://github.com/MobileTeleSystems/data-rentgen
Project-URL: CI/CD, https://github.com/MobileTeleSystems/data-rentgen/actions
Project-URL: Tracker, https://github.com/MobileTeleSystems/data-rentgen/issues
Keywords: Lineage,FastAPI,REST,FastStream
Classifier: Development Status :: 3 - Alpha
Classifier: Framework :: Pydantic
Classifier: Framework :: Pydantic :: 2
Classifier: Framework :: FastAPI
Classifier: Intended Audience :: Developers
Classifier: Operating System :: OS Independent
Classifier: Programming Language :: Python :: 3 :: Only
Classifier: Programming Language :: Python :: 3.12
Classifier: Programming Language :: Python :: 3.13
Classifier: Typing :: Typed
Requires-Python: >=3.12
License-File: LICENSE.txt
Requires-Dist: pydantic~=2.12.5
Requires-Dist: pydantic-settings~=2.12.0
Requires-Dist: typing-extensions~=4.15.0
Requires-Dist: alembic<1.19.0,>=1.17.2
Requires-Dist: sqlalchemy~=2.0.44
Requires-Dist: sqlalchemy-utils~=0.42.0
Requires-Dist: greenlet<3.4.0,>=3.2.4
Requires-Dist: pyyaml~=6.0.3
Requires-Dist: python-json-logger~=4.0.0
Requires-Dist: coloredlogs~=15.0.1
Requires-Dist: uuid6~=2025.0.0
Requires-Dist: python-dateutil~=2.9.0.post0
Requires-Dist: packaging~=25.0
Requires-Dist: cachetools~=6.2.2
Provides-Extra: server
Requires-Dist: fastapi<0.129.0,>=0.123.10; extra == "server"
Requires-Dist: starlette~=0.50.0; extra == "server"
Requires-Dist: uvicorn<0.41,>=0.38; extra == "server"
Requires-Dist: starlette-exporter~=0.23.0; extra == "server"
Requires-Dist: asgi-correlation-id~=4.3.4; extra == "server"
Requires-Dist: pyjwt~=2.10.1; extra == "server"
Requires-Dist: itsdangerous~=2.2.0; extra == "server"
Requires-Dist: python-multipart~=0.0.20; extra == "server"
Requires-Dist: python-keycloak<7.1.0,>=5.8.1; extra == "server"
Provides-Extra: consumer
Requires-Dist: faststream[cli,kafka]~=0.6.3; extra == "consumer"
Requires-Dist: cramjam~=2.11.0; extra == "consumer"
Provides-Extra: http2kafka
Requires-Dist: fastapi<0.129.0,>=0.123.10; extra == "http2kafka"
Requires-Dist: starlette~=0.50.0; extra == "http2kafka"
Requires-Dist: uvicorn<0.41,>=0.38; extra == "http2kafka"
Requires-Dist: starlette-exporter~=0.23.0; extra == "http2kafka"
Requires-Dist: asgi-correlation-id~=4.3.4; extra == "http2kafka"
Requires-Dist: faststream[cli,kafka]~=0.6.3; extra == "http2kafka"
Requires-Dist: cramjam~=2.11.0; extra == "http2kafka"
Provides-Extra: postgres
Requires-Dist: asyncpg~=0.31.0; extra == "postgres"
Provides-Extra: gssapi
Requires-Dist: gssapi~=1.10.0; extra == "gssapi"
Provides-Extra: seed
Requires-Dist: faker<40.2,>=38.2; extra == "seed"
Dynamic: license-file
